test_unstructured/__init__.py
test_unstructured/test_utils.py
test_unstructured/unit_utils.py
test_unstructured/chunking/__init__.py
test_unstructured/chunking/test_base.py
test_unstructured/chunking/test_basic.py
test_unstructured/chunking/test_dispatch.py
test_unstructured/chunking/test_title.py
test_unstructured/cleaners/__init__.py
test_unstructured/cleaners/test_core.py
test_unstructured/cleaners/test_extract.py
test_unstructured/cleaners/test_translate.py
test_unstructured/documents/__init__.py
test_unstructured/documents/test_coordinates.py
test_unstructured/documents/test_elements.py
test_unstructured/documents/test_email_elements.py
test_unstructured/embed/__init__.py
test_unstructured/embed/test_octoai.py
test_unstructured/embed/test_openai.py
test_unstructured/embed/test_vertexai.py
test_unstructured/embed/test_voyageai.py
test_unstructured/file_utils/__init__.py
test_unstructured/file_utils/test_exploration.py
test_unstructured/file_utils/test_file_conversion.py
test_unstructured/file_utils/test_filetype.py
test_unstructured/file_utils/test_metadata.py
test_unstructured/file_utils/test_model.py
test_unstructured/metrics/__init__.py
test_unstructured/metrics/test_element_type.py
test_unstructured/metrics/test_evaluate.py
test_unstructured/metrics/test_table_alignment.py
test_unstructured/metrics/test_table_detection_metrics.py
test_unstructured/metrics/test_table_formats.py
test_unstructured/metrics/test_table_structure.py
test_unstructured/metrics/test_text_extraction.py
test_unstructured/metrics/test_utils.py
test_unstructured/nlp/__init__.py
test_unstructured/nlp/mock_nltk.py
test_unstructured/nlp/test_partition.py
test_unstructured/nlp/test_tokenize.py
test_unstructured/partition/__init__.py
test_unstructured/partition/test_api.py
test_unstructured/partition/test_auto.py
test_unstructured/partition/test_common.py
test_unstructured/partition/test_constants.py
test_unstructured/partition/test_csv.py
test_unstructured/partition/test_doc.py
unstructured_cpu-0.15.1.dist-info/LICENSE.md
unstructured_cpu-0.15.1.dist-info/METADATA
unstructured_cpu-0.15.1.dist-info/WHEEL
unstructured_cpu-0.15.1.dist-info/entry_points.txt
unstructured_cpu-0.15.1.dist-info/top_level.txt
unstructured_cpu-0.15.1.dist-info/RECORD
