Metadata-Version: 2.1
Name: unstructured-cpu
Version: 0.15.1
Summary: A library that prepares raw documents for downstream ML tasks.
Home-page: https://github.com/Unstructured-IO/unstructured
Author: Unstructured Technologies
Author-email: devops@unstructuredai.io
License: Apache-2.0
Keywords: NLP PDF HTML CV XML parsing preprocessing
Classifier: Development Status :: 4 - Beta
Classifier: Intended Audience :: Developers
Classifier: Intended Audience :: Education
Classifier: Intended Audience :: Science/Research
Classifier: License :: OSI Approved :: Apache Software License
Classifier: Operating System :: OS Independent
Classifier: Programming Language :: Python :: 3
Classifier: Programming Language :: Python :: 3.9
Classifier: Programming Language :: Python :: 3.10
Classifier: Programming Language :: Python :: 3.11
Classifier: Programming Language :: Python :: 3.12
Classifier: Topic :: Scientific/Engineering :: Artificial Intelligence
Requires-Python: >=3.9.0,<3.13
License-File: LICENSE.md
Requires-Dist: chardet
Requires-Dist: filetype
Requires-Dist: python-magic
Requires-Dist: lxml
Requires-Dist: nltk
Requires-Dist: tabulate
Requires-Dist: requests
Requires-Dist: beautifulsoup4
Requires-Dist: emoji
Requires-Dist: dataclasses-json
Requires-Dist: python-iso639
Requires-Dist: langdetect
Requires-Dist: numpy <2
Requires-Dist: rapidfuzz
Requires-Dist: backoff
Requires-Dist: typing-extensions
Requires-Dist: unstructured-client
Requires-Dist: wrapt
Requires-Dist: tqdm
Requires-Dist: psutil
Provides-Extra: airtable
Requires-Dist: pyairtable ; extra == 'airtable'
Provides-Extra: all-docs
Requires-Dist: effdet ; extra == 'all-docs'
Requires-Dist: unstructured.pytesseract >=0.3.12 ; extra == 'all-docs'
Requires-Dist: pikepdf ; extra == 'all-docs'
Requires-Dist: onnx ; extra == 'all-docs'
Requires-Dist: markdown ; extra == 'all-docs'
Requires-Dist: pdf2image ; extra == 'all-docs'
Requires-Dist: google-cloud-vision ; extra == 'all-docs'
Requires-Dist: openpyxl ; extra == 'all-docs'
Requires-Dist: python-pptx <=0.6.23 ; extra == 'all-docs'
Requires-Dist: pypandoc ; extra == 'all-docs'
Requires-Dist: xlrd ; extra == 'all-docs'
Requires-Dist: pillow-heif ; extra == 'all-docs'
Requires-Dist: pytesseract ; extra == 'all-docs'
Requires-Dist: unstructured-inference ==0.7.36 ; extra == 'all-docs'
Requires-Dist: python-docx >=1.1.2 ; extra == 'all-docs'
Requires-Dist: pypdf ; extra == 'all-docs'
Requires-Dist: pdfminer.six ; extra == 'all-docs'
Requires-Dist: python-oxmsg ; extra == 'all-docs'
Requires-Dist: networkx ; extra == 'all-docs'
Requires-Dist: pandas ; extra == 'all-docs'
Provides-Extra: astra
Requires-Dist: astrapy ; extra == 'astra'
Provides-Extra: azure
Requires-Dist: adlfs ; extra == 'azure'
Requires-Dist: fsspec ; extra == 'azure'
Provides-Extra: azure-cognitive-search
Requires-Dist: azure-search-documents ; extra == 'azure-cognitive-search'
Provides-Extra: bedrock
Requires-Dist: boto3 ; extra == 'bedrock'
Requires-Dist: langchain-community ; extra == 'bedrock'
Provides-Extra: biomed
Requires-Dist: bs4 ; extra == 'biomed'
Provides-Extra: box
Requires-Dist: boxfs ; extra == 'box'
Requires-Dist: fsspec ; extra == 'box'
Provides-Extra: chroma
Requires-Dist: chromadb ; extra == 'chroma'
Requires-Dist: importlib-metadata >=7.1.0 ; extra == 'chroma'
Requires-Dist: typer <=0.9.0 ; extra == 'chroma'
Provides-Extra: clarifai
Requires-Dist: clarifai ; extra == 'clarifai'
Provides-Extra: confluence
Requires-Dist: atlassian-python-api ; extra == 'confluence'
Provides-Extra: csv
Requires-Dist: pandas ; extra == 'csv'
Provides-Extra: databricks-volumes
Requires-Dist: databricks-sdk ; extra == 'databricks-volumes'
Provides-Extra: delta-table
Requires-Dist: deltalake ; extra == 'delta-table'
Requires-Dist: fsspec ; extra == 'delta-table'
Provides-Extra: discord
Requires-Dist: discord-py ; extra == 'discord'
Provides-Extra: doc
Requires-Dist: python-docx >=1.1.2 ; extra == 'doc'
Provides-Extra: docx
Requires-Dist: python-docx >=1.1.2 ; extra == 'docx'
Provides-Extra: dropbox
Requires-Dist: dropboxdrivefs ; extra == 'dropbox'
Requires-Dist: fsspec ; extra == 'dropbox'
Provides-Extra: elasticsearch
Requires-Dist: elasticsearch[async] ; extra == 'elasticsearch'
Provides-Extra: embed-huggingface
Requires-Dist: langchain-huggingface ; extra == 'embed-huggingface'
Provides-Extra: embed-octoai
Requires-Dist: openai ; extra == 'embed-octoai'
Requires-Dist: tiktoken ; extra == 'embed-octoai'
Provides-Extra: embed-vertexai
Requires-Dist: langchain ; extra == 'embed-vertexai'
Requires-Dist: langchain-community ; extra == 'embed-vertexai'
Requires-Dist: langchain-google-vertexai ; extra == 'embed-vertexai'
Provides-Extra: embed-voyageai
Requires-Dist: langchain ; extra == 'embed-voyageai'
Requires-Dist: langchain-voyageai ; extra == 'embed-voyageai'
Provides-Extra: epub
Requires-Dist: pypandoc ; extra == 'epub'
Provides-Extra: gcs
Requires-Dist: gcsfs ; extra == 'gcs'
Requires-Dist: fsspec ; extra == 'gcs'
Requires-Dist: bs4 ; extra == 'gcs'
Provides-Extra: github
Requires-Dist: pygithub >1.58.0 ; extra == 'github'
Provides-Extra: gitlab
Requires-Dist: python-gitlab ; extra == 'gitlab'
Provides-Extra: google-drive
Requires-Dist: google-api-python-client ; extra == 'google-drive'
Provides-Extra: hubspot
Requires-Dist: hubspot-api-client ; extra == 'hubspot'
Requires-Dist: urllib3 ; extra == 'hubspot'
Provides-Extra: huggingface
Requires-Dist: langdetect ; extra == 'huggingface'
Requires-Dist: sacremoses ; extra == 'huggingface'
Requires-Dist: sentencepiece ; extra == 'huggingface'
Requires-Dist: torch ; extra == 'huggingface'
Requires-Dist: transformers ; extra == 'huggingface'
Provides-Extra: image
Requires-Dist: onnx ; extra == 'image'
Requires-Dist: pdf2image ; extra == 'image'
Requires-Dist: pdfminer.six ; extra == 'image'
Requires-Dist: pikepdf ; extra == 'image'
Requires-Dist: pillow-heif ; extra == 'image'
Requires-Dist: pypdf ; extra == 'image'
Requires-Dist: pytesseract ; extra == 'image'
Requires-Dist: google-cloud-vision ; extra == 'image'
Requires-Dist: effdet ; extra == 'image'
Requires-Dist: unstructured-inference ==0.7.36 ; extra == 'image'
Requires-Dist: unstructured.pytesseract >=0.3.12 ; extra == 'image'
Provides-Extra: jira
Requires-Dist: atlassian-python-api ; extra == 'jira'
Provides-Extra: kafka
Requires-Dist: confluent-kafka ; extra == 'kafka'
Provides-Extra: local-inference
Requires-Dist: effdet ; extra == 'local-inference'
Requires-Dist: unstructured.pytesseract >=0.3.12 ; extra == 'local-inference'
Requires-Dist: pikepdf ; extra == 'local-inference'
Requires-Dist: onnx ; extra == 'local-inference'
Requires-Dist: markdown ; extra == 'local-inference'
Requires-Dist: pdf2image ; extra == 'local-inference'
Requires-Dist: google-cloud-vision ; extra == 'local-inference'
Requires-Dist: openpyxl ; extra == 'local-inference'
Requires-Dist: python-pptx <=0.6.23 ; extra == 'local-inference'
Requires-Dist: pypandoc ; extra == 'local-inference'
Requires-Dist: xlrd ; extra == 'local-inference'
Requires-Dist: pillow-heif ; extra == 'local-inference'
Requires-Dist: pytesseract ; extra == 'local-inference'
Requires-Dist: unstructured-inference ==0.7.36 ; extra == 'local-inference'
Requires-Dist: python-docx >=1.1.2 ; extra == 'local-inference'
Requires-Dist: pypdf ; extra == 'local-inference'
Requires-Dist: pdfminer.six ; extra == 'local-inference'
Requires-Dist: python-oxmsg ; extra == 'local-inference'
Requires-Dist: networkx ; extra == 'local-inference'
Requires-Dist: pandas ; extra == 'local-inference'
Provides-Extra: md
Requires-Dist: markdown ; extra == 'md'
Provides-Extra: mongodb
Requires-Dist: pymongo ; extra == 'mongodb'
Provides-Extra: msg
Requires-Dist: python-oxmsg ; extra == 'msg'
Provides-Extra: notion
Requires-Dist: notion-client ; extra == 'notion'
Requires-Dist: htmlBuilder ; extra == 'notion'
Provides-Extra: odt
Requires-Dist: python-docx >=1.1.2 ; extra == 'odt'
Requires-Dist: pypandoc ; extra == 'odt'
Provides-Extra: onedrive
Requires-Dist: msal ; extra == 'onedrive'
Requires-Dist: Office365-REST-Python-Client ; extra == 'onedrive'
Requires-Dist: bs4 ; extra == 'onedrive'
Provides-Extra: openai
Requires-Dist: langchain-openai ; extra == 'openai'
Provides-Extra: opensearch
Requires-Dist: opensearch-py ; extra == 'opensearch'
Provides-Extra: org
Requires-Dist: pypandoc ; extra == 'org'
Provides-Extra: outlook
Requires-Dist: msal ; extra == 'outlook'
Requires-Dist: Office365-REST-Python-Client ; extra == 'outlook'
Provides-Extra: paddleocr
Requires-Dist: unstructured.paddleocr ==2.8.0.1 ; extra == 'paddleocr'
Provides-Extra: pdf
Requires-Dist: onnx ; extra == 'pdf'
Requires-Dist: pdf2image ; extra == 'pdf'
Requires-Dist: pdfminer.six ; extra == 'pdf'
Requires-Dist: pikepdf ; extra == 'pdf'
Requires-Dist: pillow-heif ; extra == 'pdf'
Requires-Dist: pypdf ; extra == 'pdf'
Requires-Dist: pytesseract ; extra == 'pdf'
Requires-Dist: google-cloud-vision ; extra == 'pdf'
Requires-Dist: effdet ; extra == 'pdf'
Requires-Dist: unstructured-inference ==0.7.36 ; extra == 'pdf'
Requires-Dist: unstructured.pytesseract >=0.3.12 ; extra == 'pdf'
Provides-Extra: pinecone
Requires-Dist: pinecone-client >=3.7.1 ; extra == 'pinecone'
Provides-Extra: postgres
Requires-Dist: psycopg2-binary ; extra == 'postgres'
Provides-Extra: ppt
Requires-Dist: python-pptx <=0.6.23 ; extra == 'ppt'
Provides-Extra: pptx
Requires-Dist: python-pptx <=0.6.23 ; extra == 'pptx'
Provides-Extra: qdrant
Requires-Dist: qdrant-client ; extra == 'qdrant'
Provides-Extra: reddit
Requires-Dist: praw ; extra == 'reddit'
Provides-Extra: rst
Requires-Dist: pypandoc ; extra == 'rst'
Provides-Extra: rtf
Requires-Dist: pypandoc ; extra == 'rtf'
Provides-Extra: s3
Requires-Dist: s3fs ; extra == 's3'
Requires-Dist: fsspec ; extra == 's3'
Provides-Extra: salesforce
Requires-Dist: simple-salesforce ; extra == 'salesforce'
Provides-Extra: sftp
Requires-Dist: fsspec ; extra == 'sftp'
Requires-Dist: paramiko ; extra == 'sftp'
Provides-Extra: sharepoint
Requires-Dist: msal ; extra == 'sharepoint'
Requires-Dist: Office365-REST-Python-Client ; extra == 'sharepoint'
Provides-Extra: singlestore
Requires-Dist: singlestoredb ; extra == 'singlestore'
Provides-Extra: slack
Requires-Dist: slack-sdk ; extra == 'slack'
Provides-Extra: tsv
Requires-Dist: pandas ; extra == 'tsv'
Provides-Extra: weaviate
Requires-Dist: weaviate-client ; extra == 'weaviate'
Provides-Extra: wikipedia
Requires-Dist: wikipedia ; extra == 'wikipedia'
Provides-Extra: xlsx
Requires-Dist: openpyxl ; extra == 'xlsx'
Requires-Dist: pandas ; extra == 'xlsx'
Requires-Dist: xlrd ; extra == 'xlsx'
Requires-Dist: networkx ; extra == 'xlsx'
